run_pylint.py
alembic/env.py
athena/__init__.py
athena/__main__.py
athena/api.py
athena/config.py
athena/db.py
athena/input_processor.py
athena/loguru_config.py
athena/prompt.py
athena/user_manager.py
athena/api_views/__init__.py
athena/api_views/chat.py
athena/llm/__init__.py
athena/llm/openai/__init__.py
athena/llm/openai/chat_completion.py
athena/llm/openai/completion.py
athena/llm/openai/constants.py
athena/llm/vicuna/__init__.py
athena/memory/__init__.py
athena/memory/redis.py
athena/memory/redis_vector.py
athena/models/__init__.py
athena/models/api.py
athena/nlu/__init__.py
athena/nlu/base.py
athena/nlu/intentions_data.py
athena/nlu/nltk_entities.py
athena/nlu/nltk_intent.py
athena/plugins/__init__.py
athena/plugins/authentication_plugin.py
athena/plugins/plugin_base.py
athena/plugins/plugin_manager.py
athena/tokenization/__init__.py
athena/tokenization/openai.py
plugins/__init__.py
plugins/arithmetic_plugin.py
athena_ai-0.0.12.dist-info/METADATA
athena_ai-0.0.12.dist-info/WHEEL
athena_ai-0.0.12.dist-info/entry_points.txt
athena_ai-0.0.12.dist-info/licenses/LICENSE
athena_ai-0.0.12.dist-info/RECORD
