Metadata-Version: 2.1
Name: athena-ai
Version: 0.0.12
Summary: Athena, an AI agent built on GPT-4 architecture, is designed for continuous learning and self-reliance. Inspired by the Greek goddess of wisdom, Athena assists users with valuable insights across various subjects. Focused on knowledge acquisition, capability improvement, and security, this AI agent leverages natural language processing and a supportive human community to grow and become a trusted, versatile companion.
Project-URL: Homepage, https://github.com/BillSchumacher/Athena
Project-URL: Bug Tracker, https://github.com/BillSchumacher/Athena
Author-email: Bill Schumacher <34168009+BillSchumacher@users.noreply.github.com>, Athena <34168009+BillSchumacher@users.noreply.github.com>
License-File: LICENSE
Classifier: License :: OSI Approved :: MIT License
Classifier: Operating System :: OS Independent
Classifier: Programming Language :: Python :: 3
Requires-Python: >=3.7
Requires-Dist: alembic
Requires-Dist: black
Requires-Dist: build
Requires-Dist: click
Requires-Dist: flask
Requires-Dist: flask-cors
Requires-Dist: flask-restx
Requires-Dist: isort
Requires-Dist: loguru
Requires-Dist: nltk
Requires-Dist: openai
Requires-Dist: psycopg2
Requires-Dist: pytest
Requires-Dist: python-dotenv
Requires-Dist: redis
Requires-Dist: scikit-learn
Requires-Dist: setuptools
Requires-Dist: sqlalchemy
Requires-Dist: tenacity
Requires-Dist: tiktoken
Requires-Dist: twine
Requires-Dist: wheel
